{
  "questions": [
    {
      "question": "Which monarch is mentioned in the Oath of Citizenship?",
      "possible_answers": [
        {
          "answer": "Queen Elizabeth the Second",
          "correct": false
        },
        {
          "answer": "King Charles the Third",
          "correct": true
        },
        {
          "answer": "King Edward the Eighth",
          "correct": false
        },
        {
          "answer": "Queen Victoria",
          "correct": false
        }
      ],
      "quote": "I swear (or affirm) That I will be faithful And bear true allegiance To His Majesty **King Charles the Third**...",
      "page_number": 2,
      "paragraph": "The Oath of Citizenship",
      "online_page": "https://www.canada.ca/en/immigration-refugees-citizenship/corporate/publications-manuals/discover-canada/read-online/oath-citizenship.html#:~:text=King%20Charles%20the%20Third"
    },
    {
      "question": "What does the Oath of Citizenship affirm about the Aboriginal and treaty rights?",
      "possible_answers": [
        {
          "answer": "It denies the recognition of these rights.",
          "correct": false
        },
        {
          "answer": "It acknowledges and denies the rights.",
          "correct": false
        },
        {
          "answer": "It recognizes and affirms the rights.",
          "correct": true
        },
        {
          "answer": "It does not mention Aboriginal and treaty rights.",
          "correct": false
        }
      ],
      "quote": "...Including the Constitution Which **recognizes and affirms** The Aboriginal and treaty rights...",
      "page_number": 2,
      "paragraph": "The Oath of Citizenship",
      "online_page": "https://www.canada.ca/en/immigration-refugees-citizenship/corporate/publications-manuals/discover-canada/read-online/oath-citizenship.html#:~:text=recognizes%20and%20affirms"
    },
    {
      "question": "To whom do Canadians profess their loyalty?",
      "possible_answers": [
        {
          "answer_text": "A document such as a constitution",
          "is_correct": false
        },
        {
          "answer_text": "A banner such as a flag",
          "is_correct": false
        },
        {
          "answer_text": "A geopolitical entity such as a country",
          "is_correct": false
        },
        {
          "answer_text": "A person who represents all Canadians",
          "is_correct": true
        }
      ],
      "quote": "In Canada, **we profess our loyalty to a person who represents all Canadians** and not to a document such as a constitution, a banner such as a flag, or a geopolitical entity such as a country.",
      "page_number": 2,
      "paragraph": "Understanding the Oath",
      "online_page": "https://www.canada.ca/en/immigration-refugees-citizenship/corporate/publications-manuals/discover-canada/read-online/oath-citizenship.html#:~:text=we%20profess%20our%20loyalty%20to%20a%20person%20who%20represents%20all%20Canadians"
    },
    {
      "question": "What must immigrants between the ages of 18 and 54 have in order to become Canadian citizens?",
      "possible_answers": [
        {
          "answer_text": "A valid passport",
          "is_correct": false
        },
        {
          "answer_text": "Adequate knowledge of English or French",
          "is_correct": true
        },
        {
          "answer_text": "A permanent job",
          "is_correct": false
        },
        {
          "answer_text": "A university degree",
          "is_correct": false
        }
      ],
      "quote": "**Immigrants between the ages of 18 and 54 must have adequate knowledge of English or French** in order to become Canadian citizens.",
      "page_number": 3,
      "paragraph": "Message to Our Readers",
      "online_page": "https://www.canada.ca/en/immigration-refugees-citizenship/corporate/publications-manuals/discover-canada/read-online/message-readers.html#:~:text=Immigrants%20between%20the%20ages%20of%2018%20and%2054%20must%20have%20adequate%20knowledge%20of%20English%20or%20French"
    },
    {
      "question": "What form of government does Canada have?",
      "possible_answers": [
        {
          "answer_text": "A federal state",
          "is_correct": false
        },
        {
          "answer_text": "A parliamentary democracy",
          "is_correct": false
        },
        {
          "answer_text": "A constitutional monarchy",
          "is_correct": false
        },
        {
          "answer_text": "All of the above",
          "is_correct": true
        }
      ],
      "quote": "Canada is **a constitutional monarchy, a parliamentary democracy and a federal state**.",
      "page_number": 3,
      "paragraph": "Message to Our Readers",
      "online_page": "https://www.canada.ca/en/immigration-refugees-citizenship/corporate/publications-manuals/discover-canada/read-online/message-readers.html#:~:text=a%20constitutional%20monarchy%2C%20a%20parliamentary%20democracy%20and%20a%20federal%20state"
    },
    {
      "question": "What are Canadian citizens required to respect?",
      "possible_answers": [
        {
          "answer_text": "Other countries' laws",
          "is_correct": false
        },
        {
          "answer_text": "Canada's laws and the rights and freedoms of others",
          "is_correct": true
        },
        {
          "answer_text": "Only the rights of other Canadians",
          "is_correct": false
        },
        {
          "answer_text": "The laws of neighboring countries",
          "is_correct": false
        }
      ],
      "quote": "Canadian citizens enjoy many rights, but Canadians also have responsibilities. They **must obey Canada\u2019s laws and respect the rights and freedoms of others**.",
      "page_number": 3,
      "paragraph": "Message to Our Readers",
      "online_page": "https://www.canada.ca/en/immigration-refugees-citizenship/corporate/publications-manuals/discover-canada/read-online/message-readers.html#:~:text=must%20obey%20Canada%E2%80%99s%20laws%20and%20respect%20the%20rights%20and%20freedoms%20of%20others"
    }
  ]
}